awspacha/__init__.py
awspacha/athena.py
awspacha/awsglue.py
awspacha/config.py
awspacha/crawler.py
awspacha/google.py
awspacha/main.py
awspacha/operacion.py
awspacha/s3.py
awspacha/sqlfile.py
awspacha/utils.py
awspacha-0.2.3.dist-info/LICENSE
awspacha-0.2.3.dist-info/METADATA
awspacha-0.2.3.dist-info/WHEEL
awspacha-0.2.3.dist-info/top_level.txt
awspacha-0.2.3.dist-info/RECORD
